README.md
setup.py
pepbox/Utils.py
pepbox/__init__.py
pepbox/controller.py
pepbox/model.py
pepbox/pepbox.py
pepbox/venn.py
pepbox/view.py
pepbox.egg-info/PKG-INFO
pepbox.egg-info/SOURCES.txt
pepbox.egg-info/dependency_links.txt
pepbox.egg-info/requires.txt
pepbox.egg-info/top_level.txt