Metadata-Version: 1.1
Name: pepbox
Version: 0.3.8
Summary: Peptide specific TCR identification based on expansion.
Home-page: UNKNOWN
Author: Jerome Lane
Author-email: jerome.lane@hotmail.com
License: UNKNOWN
Platform: UNKNOWN
Classifier: Development Status :: 3 - Alpha
Classifier: Environment :: Console
Classifier: Operating System :: OS Independent
Classifier: Intended Audience :: Science/Research
Classifier: Programming Language :: Python
Classifier: Topic :: Scientific/Engineering :: Bio-Informatics
